etc/sudoers.d/sudoers-zvmsdk
etc/zvmsdk/uwsgi-zvmsdk.conf
etc/zvmsdk/zvmsdk.conf.sample
lib/systemd/system/sdkserver.service
smtLayer/ReqHandle.py
smtLayer/__init__.py
smtLayer/changeVM.py
smtLayer/cmdVM.py
smtLayer/deleteVM.py
smtLayer/generalUtils.py
smtLayer/getHost.py
smtLayer/getVM.py
smtLayer/makeVM.py
smtLayer/migrateVM.py
smtLayer/msgs.py
smtLayer/powerVM.py
smtLayer/smapi.py
smtLayer/smt.py
smtLayer/smtCmd.py
smtLayer/smtTest.py
smtLayer/vmStatus.py
smtLayer/vmUtils.py
smtLayer/tests/__init__.py
smtLayer/tests/unit/__init__.py
smtLayer/tests/unit/base.py
smtLayer/tests/unit/test_getHost.py
smtLayer/tests/unit/test_getVM.py
smtLayer/tests/unit/test_makeVM.py
smtLayer/tests/unit/test_vmStatus.py
smtLayer/tests/unit/test_vmUtils.py
var/lib/zvmsdk/setupDisk
zVMCloudConnector-1.6.3.data/scripts/sdkserver
zVMCloudConnector-1.6.3.data/scripts/zvmsdk-gentoken
zVMCloudConnector-1.6.3.data/scripts/zvmsdk-wsgi
zvmconnector/__init__.py
zvmconnector/connector.py
zvmconnector/restclient.py
zvmconnector/socketclient.py
zvmsdk/__init__.py
zvmsdk/api.py
zvmsdk/config.py
zvmsdk/configdrive.py
zvmsdk/constants.py
zvmsdk/database.py
zvmsdk/dist.py
zvmsdk/exception.py
zvmsdk/hostops.py
zvmsdk/imageops.py
zvmsdk/log.py
zvmsdk/monitor.py
zvmsdk/networkops.py
zvmsdk/returncode.py
zvmsdk/sdkserver.py
zvmsdk/smtclient.py
zvmsdk/utils.py
zvmsdk/version.py
zvmsdk/vmops.py
zvmsdk/volumeop.py
zvmsdk/sdkwsgi/__init__.py
zvmsdk/sdkwsgi/deploy.py
zvmsdk/sdkwsgi/handler.py
zvmsdk/sdkwsgi/requestlog.py
zvmsdk/sdkwsgi/util.py
zvmsdk/sdkwsgi/handlers/__init__.py
zvmsdk/sdkwsgi/handlers/file.py
zvmsdk/sdkwsgi/handlers/guest.py
zvmsdk/sdkwsgi/handlers/healthy.py
zvmsdk/sdkwsgi/handlers/host.py
zvmsdk/sdkwsgi/handlers/image.py
zvmsdk/sdkwsgi/handlers/tokens.py
zvmsdk/sdkwsgi/handlers/version.py
zvmsdk/sdkwsgi/handlers/volume.py
zvmsdk/sdkwsgi/handlers/vswitch.py
zvmsdk/sdkwsgi/schemas/__init__.py
zvmsdk/sdkwsgi/schemas/guest.py
zvmsdk/sdkwsgi/schemas/host.py
zvmsdk/sdkwsgi/schemas/image.py
zVMCloudConnector-1.6.3.dist-info/LICENSE
zVMCloudConnector-1.6.3.dist-info/METADATA
zVMCloudConnector-1.6.3.dist-info/WHEEL
zVMCloudConnector-1.6.3.dist-info/entry_points.txt
zVMCloudConnector-1.6.3.dist-info/top_level.txt
zVMCloudConnector-1.6.3.dist-info/RECORD
