Metadata-Version: 2.1
Name: zVMCloudConnector
Version: 1.6.3
Summary: z/VM cloud management library in Python
Home-page: https://github.com/openmainframeproject/python-zvm-sdk
Author: IBM
License: ASL 2.0
Keywords: zvm cloud library
Platform: UNKNOWN
Classifier: Intended Audience :: Information Technology
Classifier: Intended Audience :: System Administrators
Classifier: License :: OSI Approved :: Apache Software License
Classifier: Operating System :: POSIX :: Linux
Classifier: Programming Language :: Python
Classifier: Programming Language :: Python :: 2
Classifier: Programming Language :: Python :: 2.7
Classifier: Programming Language :: Python :: 3
Classifier: Programming Language :: Python :: 3.5
Classifier: Programming Language :: Python :: 3.6
License-File: LICENSE
Requires-Dist: jsonschema (>=2.3.0)
Requires-Dist: netaddr (>=0.7.5)
Requires-Dist: PyJWT (>=1.0.1)
Requires-Dist: requests (>=2.6.0)
Requires-Dist: Routes (>=2.2)
Requires-Dist: six (>=1.9.0)
Requires-Dist: WebOb (>=1.2.3)
Requires-Dist: PyYAML (>=3.10)
